{
  "type": "Feature",
  "properties": {
    "iso:country": "FR",
    "sfomuseum:aircraft_model": "D.500",
    "sfomuseum:aircraft_name": "Dewoitine D.500",
    "sfomuseum:count_objects_public": 0,
    "sfomuseum:is_sfo": 1,
    "sfomuseum:placetype": "aircraft",
    "wd:instance_of": [
      "Q15056993"
    ],
    "wof:name": "Dewoitine D.500",
    "wof:placetype": "instrument",
    "wof:subordinate_of": [
      1159293715
    ]
  },
  "geometry": {"coordinates":[2.549047,46.698481],"type":"Point"}
}
