{
  "type": "Feature",
  "properties": {
    "iso:country": "US",
    "sfomuseum:aircraft_model": "CV-880-22M-3",
    "sfomuseum:aircraft_name": "Convair CV-880-22M-3",
    "sfomuseum:count_objects_public": 0,
    "sfomuseum:is_sfo": 1,
    "sfomuseum:placetype": "aircraft",
    "wof:name": "Convair CV-880-22M-3",
    "wof:placetype": "custom",
    "wof:placetype_alt": "aircraft",
    "wof:subordinate_of": [
      1159293605,
      1159290217
    ]
  },
  "geometry": {"coordinates":[-117.15529,32.72793],"type":"Point"}
}
