{
  "type": "Feature",
  "properties": {
    "date:inception_lower": "1940-01-01",
    "date:inception_upper": "1940-12-31",
    "sfomuseum:aircraft_model": "Martlet",
    "sfomuseum:manufacturer": "Grumman",
    "sfomuseum:placetype": "aircraft",
    "wof:name": "Grumman Martlet",
    "wof:placetype": "custom",
    "wof:placetype_alt": "aircraft"
  },
  "geometry": {"coordinates":[-73.485889,40.751775],"type":"Point"}
}
