{
  "type": "Feature",
  "properties": {
    "iso:country": "AN",
    "sfomuseum:aircraft_model": "70",
    "sfomuseum:aircraft_name": "Fokker 70",
    "sfomuseum:count_objects_public": 0,
    "sfomuseum:is_sfo": 1,
    "sfomuseum:placetype": "aircraft",
    "wd:instance_of": [
      "Q15056995"
    ],
    "wof:name": "Fokker 70",
    "wof:placetype": "custom",
    "wof:subordinate_of": [
      1159293619
    ]
  },
  "geometry": {"coordinates":[-68.249092,12.194274],"type":"Point"}
}
