{
  "type": "Feature",
  "properties": {
    "iso:country":"US",
    "sfomuseum:aircraft_model":"S-3A",
    "sfomuseum:aircraft_name":"Lockheed S-3A Viking",
    "sfomuseum:aircraft_variant":"Viking",
    "sfomuseum:placetype":"aircraft",
    "wd:instance_of":[
        "Q658414"
    ],
    "wof:name":"Lockheed S-3A Viking",
    "wof:placetype":"instrument",
    "wof:subordinate_of":[
        1159293697
    ]
},
  "geometry": {"coordinates":[-118.32258400000001,34.185797],"type":"Point"}
}