{
  "type": "Feature",
  "properties": {
    "iso:country": "US",
    "sfomuseum:aircraft_model": "S-3A",
    "sfomuseum:aircraft_name": "Lockheed S-3A Viking",
    "sfomuseum:aircraft_variant": "Viking",
    "sfomuseum:count_objects_public": 0,
    "sfomuseum:is_sfo": 1,
    "sfomuseum:manufacturer": "Lockheed",
    "sfomuseum:placetype": "aircraft",
    "wd:instance_of": [
      "Q658414"
    ],
    "wof:name": "Lockheed S-3A Viking",
    "wof:placetype": "custom",
    "wof:placetype_alt": "aircraft",
    "wof:subordinate_of": [
      1159293697
    ]
  },
  "geometry": {"coordinates":[-118.322584,34.185797],"type":"Point"}
}
