{
  "type": "Feature",
  "properties": {
    "iso:country": "DE",
    "sfomuseum:aircraft_model": "Bü 131A",
    "sfomuseum:aircraft_name": "Bücker Bü 131A Jungmann",
    "sfomuseum:aircraft_variant": "Jungmann",
    "sfomuseum:count_objects_public": 0,
    "sfomuseum:is_sfo": 1,
    "sfomuseum:placetype": "aircraft",
    "wof:name": "Bücker Bü 131A Jungmann",
    "wof:placetype": "custom",
    "wof:placetype_alt": "aircraft",
    "wof:subordinate_of": [
      1159293665
    ]
  },
  "geometry": {"coordinates":[13.442033,52.287696],"type":"Point"}
}
