{
  "type": "Feature",
  "properties": {
    "iso:country":"GR",
    "sfomuseum:aircraft_model":"Executive 7W",
    "sfomuseum:aircraft_name":"Spartan  Executive 7W",
    "sfomuseum:count_objects_public":0,
    "sfomuseum:placetype":"aircraft",
    "wof:name":"Spartan  Executive 7W",
    "wof:placetype":"instrument",
    "wof:subordinate_of":[
        1159294029
    ]
},
  "geometry": {"coordinates":[21.708535,39.78331],"type":"Point"}
}