{
  "type": "Feature",
  "properties": {
    "iso:country": "DE",
    "sfomuseum:count_objects_public": 1,
    "sfomuseum:is_sfo": 1,
    "sfomuseum:manufacturer": "Bücker",
    "sfomuseum:model": "Bü 133B",
    "sfomuseum:model_name": "Jungmeister ",
    "sfomuseum:name": "Bücker Bü 133B Jungmeister ",
    "sfomuseum:placetype": "aircraft",
    "wof:name": "Bücker Bü 133B Jungmeister ",
    "wof:placetype": "custom",
    "wof:placetype_alt": "aircraft",
    "wof:subordinate_of": [
      1159293665
    ]
  },
  "geometry": {"coordinates":[13.442033,52.287696],"type":"Point"}
}
