{
  "type": "Feature",
  "properties": {
    "iso:country": "FR",
    "sfomuseum:aircraft_model": "840",
    "sfomuseum:aircraft_name": "Potez 840",
    "sfomuseum:count_objects_public": 0,
    "sfomuseum:is_sfo": 1,
    "sfomuseum:placetype": "aircraft",
    "wd:instance_of": [
      "Q11436"
    ],
    "wof:name": "Potez 840",
    "wof:placetype": "custom",
    "wof:subordinate_of": [
      1159293803
    ]
  },
  "geometry": {"coordinates":[2.384788,48.910939],"type":"Point"}
}
