{
  "type": "Feature",
  "properties": {
    "iso:country": "IT",
    "millsfield:count_images": 4,
    "millsfield:count_objects": 1,
    "sfomuseum:aircraft_model": "M.C.94",
    "sfomuseum:aircraft_name": "Macchi M.C.94",
    "sfomuseum:count_objects_public": 0,
    "sfomuseum:is_sfo": 1,
    "sfomuseum:manufacturer": "Macchi",
    "sfomuseum:placetype": "aircraft",
    "wd:instance_of": [
      "Q1153376"
    ],
    "wof:name": "Macchi M.C.94",
    "wof:placetype": "custom",
    "wof:placetype_alt": "aircraft",
    "wof:subordinate_of": [
      1159293739
    ]
  },
  "geometry": {"coordinates":[8.833687,45.818949],"type":"Point"}
}
