{
  "type": "Feature",
  "properties": {
    "iso:country":"IT",
    "sfomuseum:aircraft_model":"M.C.94",
    "sfomuseum:aircraft_name":"Macchi M.C.94",
    "sfomuseum:placetype":"aircraft",
    "wd:instance_of":[
        "Q1153376"
    ],
    "wof:name":"Macchi M.C.94",
    "wof:placetype":"instrument",
    "wof:subordinate_of":[
        1159293739
    ]
},
  "geometry": {"coordinates":[8.833687,45.818949],"type":"Point"}
}