{
  "type": "Feature",
  "properties": {
    "iso:country":"DE",
    "sfomuseum:aircraft_model":"Ju 46",
    "sfomuseum:aircraft_name":"Junkers Ju 46",
    "sfomuseum:count_objects_public":0,
    "sfomuseum:placetype":"aircraft",
    "wd:instance_of":[
        "Q11436"
    ],
    "wof:name":"Junkers Ju 46",
    "wof:placetype":"instrument",
    "wof:subordinate_of":[
        1159294171
    ]
},
  "geometry": {"coordinates":[12.2236,51.829379],"type":"Point"}
}