{
  "type": "Feature",
  "properties": {
    "iso:country":"RU",
    "sfomuseum:aircraft_model":"Tu-144",
    "sfomuseum:aircraft_name":"Tupolev Tu-144",
    "sfomuseum:count_objects_public":3,
    "sfomuseum:is_sfo":1,
    "sfomuseum:placetype":"aircraft",
    "wd:instance_of":[
        "Q15056995"
    ],
    "wof:name":"Tupolev Tu-144",
    "wof:placetype":"instrument",
    "wof:subordinate_of":[
        1159294153
    ]
},
  "geometry": {"coordinates":[37.615561,55.741469],"type":"Point"}
}