{
  "type": "Feature",
  "properties": {
    "date:inception_lower": "2014-01-01",
    "date:inception_upper": "2014-12-31",
    "iso:country": "BR",
    "sfomuseum:placetype": "aircraft",
    "wof:name": "Embraer Legacy 500",
    "wof:placetype": "custom",
    "wof:placetype_alt": [
      "aircraft"
    ]
  },
  "geometry": {"coordinates":[-45.859225,-23.236577],"type":"Point"}
}
