{
  "type": "Feature",
  "properties": {
    "iso:country":"BR",
    "sfomuseum:placetype":"aircraft",
    "wof:name":"Embraer Legacy 500",
    "wof:placetype":"instrument"
},
  "geometry": {"coordinates":[-45.859225,-23.236577],"type":"Point"}
}