{
  "type": "Feature",
  "properties": {
    "date:inception_lower": "1915-01-01",
    "date:inception_upper": "1915-12-31",
    "sfomuseum:aircraft_model": "Baby",
    "sfomuseum:aircraft_name": "Sopwith Baby",
    "sfomuseum:is_sfo": 1,
    "sfomuseum:manufacturer": "Sopwith",
    "sfomuseum:placetype": "aircraft",
    "wof:name": "Sopwith Baby",
    "wof:placetype": "custom",
    "wof:placetype_alt": "aircraft"
  },
  "geometry": {"coordinates":[-0.310941,51.409565],"type":"Point"}
}
