{
  "type": "Feature",
  "properties": {
    "iso:country": "FR",
    "millsfield:count_images": 4,
    "millsfield:count_objects": 1,
    "sfomuseum:aircraft_model": "C.450",
    "sfomuseum:aircraft_name": "Caudron C.450",
    "sfomuseum:count_objects_public": 0,
    "sfomuseum:is_sfo": 1,
    "sfomuseum:manufacturer": "Caudron",
    "sfomuseum:placetype": "aircraft",
    "wd:instance_of": [
      "Q15056995"
    ],
    "wof:name": "Caudron C.450",
    "wof:placetype": "custom",
    "wof:placetype_alt": [
      "aircraft"
    ],
    "wof:subordinate_of": [
      1159294227
    ]
  },
  "geometry": {"coordinates":[2.264404,48.823024],"type":"Point"}
}
