{
  "type": "Feature",
  "properties": {
    "iso:country":"FR",
    "sfomuseum:aircraft_model":"C.450",
    "sfomuseum:aircraft_name":"Caudron C.450",
    "sfomuseum:placetype":"aircraft",
    "wd:instance_of":[
        "Q15056995"
    ],
    "wof:name":"Caudron C.450",
    "wof:placetype":"instrument",
    "wof:subordinate_of":[
        1159294227
    ]
},
  "geometry": {"coordinates":[2.264404,48.823024],"type":"Point"}
}