{
  "type": "Feature",
  "properties": {
    "iso:country": "GB",
    "sfomuseum:aircraft_name": "Hawker Siddeley Sea Harrier",
    "sfomuseum:aircraft_variant": "Sea Harrier",
    "sfomuseum:count_objects_public": 0,
    "sfomuseum:is_sfo": 1,
    "sfomuseum:manufacturer": "Hawker Siddeley",
    "sfomuseum:placetype": "aircraft",
    "wof:name": "Hawker Siddeley Sea Harrier",
    "wof:placetype": "custom",
    "wof:placetype_alt": "aircraft",
    "wof:subordinate_of": [
      1159294003
    ]
  },
  "geometry": {"coordinates":[-1.247349,52.418788],"type":"Point"}
}
