{
  "type": "Feature",
  "properties": {
    "iso:country": "US",
    "sfomuseum:aircraft_model": "VS-300",
    "sfomuseum:count_objects_public": 1,
    "sfomuseum:is_sfo": 1,
    "sfomuseum:manufacturer": "Sikorsky (USA)",
    "sfomuseum:model": "VS-300",
    "sfomuseum:name": "Sikorsky (USA) VS-300",
    "sfomuseum:placetype": "aircraft",
    "wof:name": "Sikorsky (USA) VS-300",
    "wof:placetype": "custom",
    "wof:placetype_alt": "aircraft",
    "wof:subordinate_of": [
      1159293917
    ]
  },
  "geometry": {"coordinates":[-96.999668,39.715956],"type":"Point"}
}
