{
  "type": "Feature",
  "properties": {
    "iso:country": "CA",
    "sfomuseum:aircraft_name": "Noorduyn Norseman IV",
    "sfomuseum:aircraft_variant": "Norseman IV",
    "sfomuseum:count_objects_public": 0,
    "sfomuseum:is_sfo": 1,
    "sfomuseum:placetype": "aircraft",
    "wof:name": "Noorduyn Norseman IV",
    "wof:placetype": "custom",
    "wof:placetype_alt": "aircraft",
    "wof:subordinate_of": [
      1159294273
    ]
  },
  "geometry": {"coordinates":[-73.587778,45.508889],"type":"Point"}
}
