{
  "type": "Feature",
  "properties": {
    "date:inception_lower": "1971-01-01",
    "date:inception_upper": "1971-12-31",
    "iso:country": "US",
    "sfomuseum:aircraft_model": "7ACA",
    "sfomuseum:aircraft_modelname": "Champ",
    "sfomuseum:aircraft_name": "Bellanca 7ACA Champ",
    "sfomuseum:aircraft_variant": "Champ",
    "sfomuseum:count_objects_public": 0,
    "sfomuseum:is_sfo": 1,
    "sfomuseum:manufacturer": "Bellanca",
    "sfomuseum:placetype": "aircraft",
    "wof:name": "Bellanca 7ACA Champ",
    "wof:placetype": "custom",
    "wof:placetype_alt": [
      "aircraft"
    ],
    "wof:subordinate_of": [
      1159294087
    ]
  },
  "geometry": {"coordinates":[-95.370488,45.868571],"type":"Point"}
}
