{
  "type": "Feature",
  "properties": {
    "iso:country": "GB",
    "sfomuseum:aircraft_model": "Jetstream 31",
    "sfomuseum:aircraft_name": "BAe Jetstream 31",
    "sfomuseum:count_objects_public": 2,
    "sfomuseum:is_sfo": 1,
    "sfomuseum:manufacturer": "BAe",
    "sfomuseum:placetype": "aircraft",
    "wd:instance_of": [
      "Q15056993"
    ],
    "wof:name": "BAe Jetstream 31",
    "wof:placetype": "custom",
    "wof:placetype_alt": "aircraft",
    "wof:subordinate_of": [
      1159293749
    ]
  },
  "geometry": {"coordinates":[0.068077,51.360473],"type":"Point"}
}
