{
  "type": "Feature",
  "properties": {
    "iso:country":"GB",
    "sfomuseum:aircraft_name":"Supermarine Spitfire Mk.VB",
    "sfomuseum:aircraft_variant":"Spitfire Mk.VB",
    "sfomuseum:placetype":"aircraft",
    "wd:instance_of":[
        "Q15056993"
    ],
    "wof:name":"Supermarine Spitfire Mk.VB",
    "wof:placetype":"instrument",
    "wof:subordinate_of":[
        1159294325
    ]
},
  "geometry": {"coordinates":[-1.247349,52.418788],"type":"Point"}
}