{
  "type": "Feature",
  "properties": {
    "iso:country": "US",
    "sfomuseum:aircraft_model": "PN-9",
    "sfomuseum:aircraft_name": "Naval Aircraft Factory PN-9",
    "sfomuseum:count_objects_public": 0,
    "sfomuseum:is_sfo": 1,
    "sfomuseum:manufacturer": "Naval Aircraft Factory",
    "sfomuseum:placetype": "aircraft",
    "wd:instance_of": [
      "Q15056995"
    ],
    "wof:name": "Naval Aircraft Factory PN-9",
    "wof:placetype": "custom",
    "wof:placetype_alt": "aircraft",
    "wof:subordinate_of": [
      1159293659
    ]
  },
  "geometry": {"coordinates":[-96.999668,39.715956],"type":"Point"}
}
