{
  "type": "Feature",
  "properties": {
    "iso:country": "GB",
    "sfomuseum:aircraft_model": "D.H.88 Comet",
    "sfomuseum:aircraft_name": "de Havilland D.H.88 Comet",
    "sfomuseum:count_objects_public": 0,
    "sfomuseum:is_sfo": 1,
    "sfomuseum:placetype": "aircraft",
    "wd:instance_of": [
      "Q11436"
    ],
    "wof:name": "de Havilland D.H.88 Comet",
    "wof:placetype": "instrument",
    "wof:subordinate_of": [
      1159293995
    ]
  },
  "geometry": {"coordinates":[-0.145641,51.846273],"type":"Point"}
}
