{
  "type": "Feature",
  "properties": {
    "date:inception_lower": "1936-01-01",
    "date:inception_upper": "1936-12-31",
    "millsfield:count_images": 1,
    "millsfield:count_objects": 1,
    "sfomuseum:aircraft_model": "PC-3",
    "sfomuseum:aircraft_name": "Aeronca PC-3",
    "sfomuseum:is_sfo": 1,
    "sfomuseum:manufacturer": "Aeronca",
    "sfomuseum:placetype": "aircraft",
    "wof:name": "Aeronca PC-3",
    "wof:placetype": "custom",
    "wof:placetype_alt": "aircraft"
  },
  "geometry": {"coordinates":[-84.371092,39.50188],"type":"Point"}
}
