{
  "type": "Feature",
  "properties": {
    "iso:country": "IT",
    "sfomuseum:aircraft_model": "G.91",
    "sfomuseum:aircraft_name": "Fiat G.91",
    "sfomuseum:count_objects_public": 0,
    "sfomuseum:is_sfo": 1,
    "sfomuseum:manufacturer": "Fiat",
    "sfomuseum:placetype": "aircraft",
    "wd:instance_of": [
      "Q15056993"
    ],
    "wof:name": "Fiat G.91",
    "wof:placetype": "custom",
    "wof:placetype_alt": "aircraft",
    "wof:subordinate_of": [
      1159294013
    ]
  },
  "geometry": {"coordinates":[7.652514,45.059405],"type":"Point"}
}
