{
  "type": "Feature",
  "properties": {
    "iso:country":"FR",
    "sfomuseum:aircraft_model":"NiD 622",
    "sfomuseum:aircraft_name":"Nieuport NiD 622",
    "sfomuseum:placetype":"aircraft",
    "wof:name":"Nieuport NiD 622",
    "wof:placetype":"instrument",
    "wof:subordinate_of":[
        1159294179
    ]
},
  "geometry": {"coordinates":[2.219949,48.870189],"type":"Point"}
}