{
  "type": "Feature",
  "properties": {
    "iso:country":"FR",
    "sfomuseum:aircraft_model":"D.520",
    "sfomuseum:aircraft_name":"Dewoitine D.520",
    "sfomuseum:placetype":"aircraft",
    "wd:instance_of":[
        "Q11436"
    ],
    "wof:name":"Dewoitine D.520",
    "wof:placetype":"instrument",
    "wof:subordinate_of":[
        1159293715
    ]
},
  "geometry": {"coordinates":[2.549047,46.698481],"type":"Point"}
}