{
  "type": "Feature",
  "properties": {
    "iso:country":"JP",
    "sfomuseum:aircraft_model":"K5Y",
    "sfomuseum:aircraft_name":"Yokosuka K5Y Willow",
    "sfomuseum:aircraft_variant":"Willow",
    "sfomuseum:placetype":"aircraft",
    "wof:name":"Yokosuka K5Y Willow",
    "wof:placetype":"instrument",
    "wof:subordinate_of":[
        1159294135
    ]
},
  "geometry": {"coordinates":[138.44189900000001,36.13793],"type":"Point"}
}