{
  "type": "Feature",
  "properties": {
    "iso:country": "JP",
    "sfomuseum:aircraft_model": "K5Y",
    "sfomuseum:aircraft_name": "Yokosuka K5Y Willow",
    "sfomuseum:aircraft_variant": "Willow",
    "sfomuseum:count_objects_public": 0,
    "sfomuseum:is_sfo": 1,
    "sfomuseum:placetype": "aircraft",
    "wof:name": "Yokosuka K5Y Willow",
    "wof:placetype": "custom",
    "wof:subordinate_of": [
      1159294135
    ]
  },
  "geometry": {"coordinates":[138.441899,36.13793],"type":"Point"}
}
