{
  "type": "Feature",
  "properties": {
    "date:cessation_lower": "2006-01-01",
    "date:cessation_upper": "2006-12-31",
    "date:inception_lower": "1975-01-01",
    "date:inception_upper": "1975-12-31",
    "sfomuseum:aircraft_model": "T-2",
    "sfomuseum:manufacturer": "Mitsubishi",
    "sfomuseum:placetype": "aircraft",
    "wof:name": "Mitsubishi T-2",
    "wof:placetype": "custom",
    "wof:placetype_alt": "aircraft"
  },
  "geometry": {"coordinates":[139.393288,35.675099],"type":"Point"}
}
