{
  "type": "Feature",
  "properties": {
    "iso:country": "GB",
    "sfomuseum:aircraft_model": "C.19 Mk IV",
    "sfomuseum:aircraft_name": "Cierva C.19 Mk IV",
    "sfomuseum:count_objects_public": 0,
    "sfomuseum:is_sfo": 1,
    "sfomuseum:manufacturer": "Cierva",
    "sfomuseum:placetype": "aircraft",
    "wof:name": "Cierva C.19 Mk IV",
    "wof:placetype": "custom",
    "wof:placetype_alt": "aircraft",
    "wof:subordinate_of": [
      1159294267
    ]
  },
  "geometry": {"coordinates":[-1.247349,52.418788],"type":"Point"}
}
