{
  "type": "Feature",
  "properties": {
    "iso:country":"US",
    "sfomuseum:aircraft_name":"Rearwin Speedster 6000",
    "sfomuseum:aircraft_variant":"Speedster 6000",
    "sfomuseum:count_objects_public":0,
    "sfomuseum:placetype":"aircraft",
    "wof:name":"Rearwin Speedster 6000",
    "wof:placetype":"instrument",
    "wof:subordinate_of":[
        1159294081
    ]
},
  "geometry": {"coordinates":[-98.38042900000001,38.500327],"type":"Point"}
}