{
  "type": "Feature",
  "properties": {
    "millsfield:count_images": 5,
    "millsfield:count_objects": 5,
    "sfomuseum:aircraft_model": "2000",
    "sfomuseum:aircraft_name": "Travel Air 2000",
    "sfomuseum:is_sfo": 1,
    "sfomuseum:manufacturer": "Travel Air",
    "sfomuseum:placetype": "aircraft",
    "wof:name": "Travel Air 2000",
    "wof:placetype": "custom",
    "wof:placetype_alt": "aircraft"
  },
  "geometry": {"coordinates":[-96.999668,39.715956],"type":"Point"}
}
