{
  "type": "Feature",
  "properties": {
    "iso:country":"FR",
    "sfomuseum:aircraft_model":"117 R2",
    "sfomuseum:aircraft_name":"Mureaux 117 R2",
    "sfomuseum:count_objects_public":0,
    "sfomuseum:is_sfo":1,
    "sfomuseum:placetype":"aircraft",
    "wof:name":"Mureaux 117 R2",
    "wof:placetype":"instrument",
    "wof:subordinate_of":[
        1159294283
    ]
},
  "geometry": {"coordinates":[2.549047,46.698481],"type":"Point"}
}