{
  "type": "Feature",
  "properties": {
    "iso:country": "GB",
    "sfomuseum:aircraft_model": "F.4",
    "sfomuseum:aircraft_name": "Martinsyde F.4 Buzzard",
    "sfomuseum:aircraft_variant": "Buzzard",
    "sfomuseum:count_objects_public": 0,
    "sfomuseum:is_sfo": 1,
    "sfomuseum:placetype": "aircraft",
    "wd:instance_of": [
      "Q18491037"
    ],
    "wof:name": "Martinsyde F.4 Buzzard",
    "wof:placetype": "instrument",
    "wof:subordinate_of": [
      1159294191
    ]
  },
  "geometry": {"coordinates":[-0.568148,51.317541],"type":"Point"}
}
