{
  "type": "Feature",
  "properties": {
    "iso:country": "US",
    "sfomuseum:aircraft_model": "F4U",
    "sfomuseum:aircraft_name": "Vought F4U",
    "sfomuseum:count_objects_public": 0,
    "sfomuseum:is_sfo": 1,
    "sfomuseum:placetype": "aircraft",
    "wd:instance_of": [
      "Q15056993"
    ],
    "wof:name": "Vought F4U",
    "wof:placetype": "custom",
    "wof:subordinate_of": [
      1159293877
    ]
  },
  "geometry": {"coordinates":[-96.784359,32.736212],"type":"Point"}
}
