{
  "type": "Feature",
  "properties": {
    "iso:country":"FR",
    "sfomuseum:aircraft_model":"A318",
    "sfomuseum:aircraft_name":"Airbus A318",
    "sfomuseum:placetype":"aircraft",
    "wd:instance_of":[
        "Q15056995"
    ],
    "wof:name":"Airbus A318",
    "wof:placetype":"instrument",
    "wof:subordinate_of":[
        1159293829
    ]
},
  "geometry": {"coordinates":[1.382665,43.634465],"type":"Point"}
}