{
  "type": "Feature",
  "properties": {
    "date:inception_lower": "1914-01-01",
    "date:inception_upper": "1914-12-31",
    "millsfield:count_images": 4,
    "millsfield:count_objects": 1,
    "sfomuseum:aircraft_model": "MF.11",
    "sfomuseum:aircraft_modelname": "Shorthorn",
    "sfomuseum:aircraft_name": "Farman MF.11 Shorthorn",
    "sfomuseum:is_sfo": 1,
    "sfomuseum:manufacturer": "Farman",
    "sfomuseum:placetype": "aircraft",
    "wof:name": "Farman MF.11 Shorthorn",
    "wof:placetype": "custom",
    "wof:placetype_alt": [
      "aircraft"
    ]
  },
  "geometry": {"coordinates":[2.104872,48.750889],"type":"Point"}
}
