{
  "type": "Feature",
  "properties": {
    "sfomuseum:aircraft_model": "XPBS-1",
    "sfomuseum:aircraft_name": "Sikorsky (USA) XPBS-1",
    "sfomuseum:is_sfo": 1,
    "sfomuseum:manufacturer": "Sikorsky (USA)",
    "sfomuseum:placetype": "aircraft",
    "wof:name": "Sikorsky (USA) XPBS-1",
    "wof:placetype": "custom",
    "wof:placetype_alt": "aircraft"
  },
  "geometry": {"coordinates":[-96.999668,39.715956],"type":"Point"}
}
