{
  "type": "Feature",
  "properties": {
    "iso:country": "GB",
    "millsfield:count_images": 6,
    "millsfield:count_objects": 5,
    "sfomuseum:aircraft_modelname": "Viscount",
    "sfomuseum:aircraft_name": "Vickers Viscount",
    "sfomuseum:aircraft_variant": "Viscount",
    "sfomuseum:count_objects_public": 5,
    "sfomuseum:is_sfo": 1,
    "sfomuseum:manufacturer": "Vickers",
    "sfomuseum:placetype": "aircraft",
    "wd:instance_of": [
      "Q15056993"
    ],
    "wof:name": "Vickers Viscount",
    "wof:placetype": "custom",
    "wof:placetype_alt": "aircraft",
    "wof:subordinate_of": [
      1159293777
    ]
  },
  "geometry": {"coordinates":[-3.21349,54.109117],"type":"Point"}
}
