{
  "type": "Feature",
  "properties": {
    "iso:country": "GB",
    "sfomuseum:aircraft_name": "Boulton Paul Defiant MK.I",
    "sfomuseum:aircraft_variant": "Defiant MK.I",
    "sfomuseum:count_objects_public": 0,
    "sfomuseum:is_sfo": 1,
    "sfomuseum:manufacturer": "Boulton Paul",
    "sfomuseum:placetype": "aircraft",
    "wof:name": "Boulton Paul Defiant MK.I",
    "wof:placetype": "custom",
    "wof:placetype_alt": "aircraft",
    "wof:subordinate_of": [
      1159294051
    ]
  },
  "geometry": {"coordinates":[1.294508,52.650229],"type":"Point"}
}
