{
  "type": "Feature",
  "properties": {
    "iso:country":"GB",
    "sfomuseum:aircraft_name":"Boulton Paul Defiant MK.I",
    "sfomuseum:aircraft_variant":"Defiant MK.I",
    "sfomuseum:placetype":"aircraft",
    "wof:name":"Boulton Paul Defiant MK.I",
    "wof:placetype":"instrument",
    "wof:subordinate_of":[
        1159294051
    ]
},
  "geometry": {"coordinates":[1.294508,52.650229],"type":"Point"}
}