{
  "type": "Feature",
  "properties": {
    "date:inception_lower": "1942-01-01",
    "date:inception_upper": "1942-12-31",
    "sfomuseum:aircraft_model": "Seafire",
    "sfomuseum:manufacturer": "Supermarine",
    "sfomuseum:placetype": "aircraft",
    "wof:name": "Supermarine Seafire",
    "wof:placetype": "custom",
    "wof:placetype_alt": "aircraft"
  },
  "geometry": {"coordinates":[-1.247349,52.418788],"type":"Point"}
}
