{
  "type": "Feature",
  "properties": {
    "iso:country": "GB",
    "millsfield:count_images": 3,
    "millsfield:count_objects": 2,
    "sfomuseum:aircraft_model": "Spitfire",
    "sfomuseum:aircraft_name": "Supermarine Spitfire",
    "sfomuseum:aircraft_variant": "Spitfire",
    "sfomuseum:count_objects_public": 2,
    "sfomuseum:is_sfo": 1,
    "sfomuseum:manufacturer": "Supermarine",
    "sfomuseum:placetype": "aircraft",
    "wd:instance_of": [
      "Q15056993"
    ],
    "wof:name": "Supermarine Spitfire",
    "wof:placetype": "custom",
    "wof:placetype_alt": "aircraft",
    "wof:subordinate_of": [
      1159294325
    ]
  },
  "geometry": {"coordinates":[-1.247349,52.418788],"type":"Point"}
}
