{
  "type": "Feature",
  "properties": {
    "millsfield:count_images": 1,
    "millsfield:count_objects": 1,
    "sfomuseum:aircraft_model": "Vimy",
    "sfomuseum:aircraft_modelname": "Commercial",
    "sfomuseum:aircraft_name": "Vickers Vimy Commercial",
    "sfomuseum:is_sfo": 1,
    "sfomuseum:manufacturer": "Vickers",
    "sfomuseum:placetype": "aircraft",
    "wof:name": "Vickers Vimy Commercial",
    "wof:placetype": "custom",
    "wof:placetype_alt": [
      "aircraft"
    ]
  },
  "geometry": {"coordinates":[-3.21349,54.109117],"type":"Point"}
}
