{
  "type": "Feature",
  "properties": {
    "date:inception_lower": "1955-01-01",
    "date:inception_upper": "1955-12-31",
    "iso:country": "US",
    "millsfield:count_images": 4,
    "millsfield:count_objects": 1,
    "sfomuseum:aircraft_model": "Model 1049G",
    "sfomuseum:aircraft_modelname": "Super Constellation",
    "sfomuseum:aircraft_name": "Lockheed Model 1049G Super Constellation",
    "sfomuseum:aircraft_variant": "Super Constellation",
    "sfomuseum:count_objects_public": 0,
    "sfomuseum:is_sfo": 1,
    "sfomuseum:manufacturer": "Lockheed",
    "sfomuseum:placetype": "aircraft",
    "wof:name": "Lockheed Model 1049G Super Constellation",
    "wof:placetype": "custom",
    "wof:placetype_alt": "aircraft",
    "wof:subordinate_of": [
      1159293697
    ]
  },
  "geometry": {"coordinates":[-118.322584,34.185797],"type":"Point"}
}
