{
  "type": "Feature",
  "properties": {
    "iso:country": "DE",
    "sfomuseum:aircraft_model": "Tornado",
    "sfomuseum:aircraft_name": "Panavia Tornado",
    "sfomuseum:aircraft_variant": "Tornado",
    "sfomuseum:count_objects_public": 0,
    "sfomuseum:is_sfo": 1,
    "sfomuseum:manufacturer": "Panavia",
    "sfomuseum:placetype": "aircraft",
    "wd:instance_of": [
      "Q15056993"
    ],
    "wof:name": "Panavia Tornado",
    "wof:placetype": "custom",
    "wof:placetype_alt": "aircraft",
    "wof:subordinate_of": [
      1159293767
    ]
  },
  "geometry": {"coordinates":[11.750298,48.327097],"type":"Point"}
}
