{
  "type": "Feature",
  "properties": {
    "iso:country": "GB",
    "sfomuseum:aircraft_model": "B.E.2e",
    "sfomuseum:aircraft_name": "Royal Aircraft Factory (RAF) B.E.2e",
    "sfomuseum:count_objects_public": 0,
    "sfomuseum:is_sfo": 1,
    "sfomuseum:manufacturer": "Royal Aircraft Factory (RAF)",
    "sfomuseum:placetype": "aircraft",
    "wof:name": "Royal Aircraft Factory (RAF) B.E.2e",
    "wof:placetype": "custom",
    "wof:placetype_alt": [
      "aircraft"
    ],
    "wof:subordinate_of": [
      1159293587
    ]
  },
  "geometry": {"coordinates":[-1.247349,52.418788],"type":"Point"}
}
