{
  "type": "Feature",
  "properties": {
    "iso:country":"US",
    "sfomuseum:aircraft_model":"747SP",
    "sfomuseum:aircraft_name":"Boeing 747SP",
    "sfomuseum:count_objects_public":10,
    "sfomuseum:instance_of":1159289873,
    "sfomuseum:is_sfo":1,
    "sfomuseum:placetype":"aircraft",
    "wd:instance_of":[
        "Q15056995"
    ],
    "wof:coterminous":1159289873,
    "wof:name":"Boeing 747SP",
    "wof:placetype":"instrument",
    "wof:subordinate_of":[
        1159293593,
        1159289873
    ]
},
  "geometry": {"coordinates":[-122.331537,47.673455],"type":"Point"}
}