{
  "type": "Feature",
  "properties": {
    "iso:country": "US",
    "millsfield:count_images": 101,
    "millsfield:count_objects": 47,
    "sfomuseum:aircraft_model": "747SP",
    "sfomuseum:aircraft_name": "Boeing 747SP",
    "sfomuseum:count_objects_public": 10,
    "sfomuseum:instance_of": 1159289873,
    "sfomuseum:is_sfo": 1,
    "sfomuseum:manufacturer": "Boeing",
    "sfomuseum:placetype": "aircraft",
    "wd:instance_of": [
      "Q15056995"
    ],
    "wof:coterminous": 1159289873,
    "wof:name": "Boeing 747SP",
    "wof:placetype": "custom",
    "wof:placetype_alt": "aircraft",
    "wof:subordinate_of": [
      1159293593,
      1159289873
    ]
  },
  "geometry": {"coordinates":[-122.331537,47.673455],"type":"Point"}
}
