{
  "type": "Feature",
  "properties": {
    "iso:country": "US",
    "sfomuseum:aircraft_model": "E-2A (W2F-1)",
    "sfomuseum:aircraft_name": "Grumman E-2A (W2F-1) Hawkeye",
    "sfomuseum:aircraft_variant": "Hawkeye",
    "sfomuseum:count_objects_public": 0,
    "sfomuseum:is_sfo": 1,
    "sfomuseum:placetype": "aircraft",
    "wof:name": "Grumman E-2A (W2F-1) Hawkeye",
    "wof:placetype": "instrument",
    "wof:subordinate_of": [
      1159293563
    ]
  },
  "geometry": {"coordinates":[-73.485889,40.751775],"type":"Point"}
}
