{
  "type": "Feature",
  "properties": {
    "iso:country": "JP",
    "millsfield:count_images": 4,
    "millsfield:count_objects": 1,
    "sfomuseum:aircraft_model": "MU-2",
    "sfomuseum:aircraft_name": "Mitsubishi MU-2",
    "sfomuseum:count_objects_public": 0,
    "sfomuseum:is_sfo": 1,
    "sfomuseum:manufacturer": "Mitsubishi",
    "sfomuseum:placetype": "aircraft",
    "wd:instance_of": [
      "Q11436"
    ],
    "wof:name": "Mitsubishi MU-2",
    "wof:placetype": "custom",
    "wof:placetype_alt": [
      "aircraft"
    ],
    "wof:subordinate_of": [
      1159294053
    ]
  },
  "geometry": {"coordinates":[139.393288,35.675099],"type":"Point"}
}
