{
  "type": "Feature",
  "properties": {
    "iso:country":"GB",
    "sfomuseum:aircraft_name":"British Aerospace Jetstream 41",
    "sfomuseum:aircraft_variant":"Jetstream 41",
    "sfomuseum:count_objects_public":2,
    "sfomuseum:placetype":"aircraft",
    "wd:instance_of":[
        "Q11436"
    ],
    "wof:name":"British Aerospace Jetstream 41",
    "wof:placetype":"instrument",
    "wof:subordinate_of":[
        1159294331
    ]
},
  "geometry": {"coordinates":[0.068077,51.360473],"type":"Point"}
}