{
  "type": "Feature",
  "properties": {
    "iso:country": "GB",
    "sfomuseum:aircraft_model": "594",
    "sfomuseum:aircraft_name": "Avro 594 Avian",
    "sfomuseum:aircraft_variant": "Avian",
    "sfomuseum:count_objects_public": 0,
    "sfomuseum:is_sfo": 1,
    "sfomuseum:placetype": "aircraft",
    "wd:instance_of": [
      "Q11436"
    ],
    "wof:name": "Avro 594 Avian",
    "wof:placetype": "instrument",
    "wof:subordinate_of": [
      1159293981
    ]
  },
  "geometry": {"coordinates":[-1.247349,52.418788],"type":"Point"}
}
