{
  "type": "Feature",
  "properties": {
    "iso:country": "GB",
    "sfomuseum:aircraft_model": "DH-60",
    "sfomuseum:aircraft_modelname": "Moth",
    "sfomuseum:aircraft_name": "de Havilland DH-60 Moth",
    "sfomuseum:aircraft_variant": "Moth",
    "sfomuseum:count_objects_public": 1,
    "sfomuseum:is_sfo": 1,
    "sfomuseum:manufacturer": "de Havilland",
    "sfomuseum:placetype": "aircraft",
    "wof:name": "de Havilland DH-60 Moth",
    "wof:placetype": "custom",
    "wof:placetype_alt": "aircraft",
    "wof:subordinate_of": [
      1159293995
    ]
  },
  "geometry": {"coordinates":[-0.145641,51.846273],"type":"Point"}
}
