{
  "type": "Feature",
  "properties": {
    "sfomuseum:aircraft_model": "Type D",
    "sfomuseum:aircraft_name": "Blackburn  Type D",
    "sfomuseum:is_sfo": 1,
    "sfomuseum:manufacturer": "Blackburn ",
    "sfomuseum:placetype": "aircraft",
    "wof:name": "Blackburn  Type D",
    "wof:placetype": "custom",
    "wof:placetype_alt": "aircraft"
  },
  "geometry": {"coordinates":[-1.247349,52.418788],"type":"Point"}
}
