{
  "type": "Feature",
  "properties": {
    "date:inception_lower": "2002-01-01",
    "date:inception_upper": "2002-12-31",
    "iso:country": "BR",
    "sfomuseum:is_sfo": 0,
    "sfomuseum:placetype": "aircraft",
    "wd:country": "Q155",
    "wd:instance_of": [
      "Q15056993"
    ],
    "wof:name": "Embraer 175",
    "wof:placetype": "custom",
    "wof:placetype_alt": "aircraft"
  },
  "geometry": {"coordinates":[-45.859225,-23.236577],"type":"Point"}
}
