{
  "type": "Feature",
  "properties": {
    "iso:country": "US",
    "sfomuseum:aircraft_model": "CR-3",
    "sfomuseum:aircraft_name": "Curtiss CR-3",
    "sfomuseum:count_objects_public": 0,
    "sfomuseum:is_sfo": 1,
    "sfomuseum:manufacturer": "Curtiss",
    "sfomuseum:placetype": "aircraft",
    "wd:instance_of": [
      "Q15056993"
    ],
    "wof:name": "Curtiss CR-3",
    "wof:placetype": "custom",
    "wof:placetype_alt": "aircraft",
    "wof:subordinate_of": [
      1159293889
    ]
  },
  "geometry": {"coordinates":[-78.852901,42.890831],"type":"Point"}
}
