{
  "type": "Feature",
  "properties": {
    "iso:country": "DE",
    "sfomuseum:aircraft_model": "G 23",
    "sfomuseum:aircraft_name": "Junkers G 23 Generalfieldmarchall von Hinderburg",
    "sfomuseum:aircraft_variant": "Generalfieldmarchall von Hinderburg",
    "sfomuseum:count_objects_public": 0,
    "sfomuseum:is_sfo": 1,
    "sfomuseum:manufacturer": "Junkers",
    "sfomuseum:placetype": "aircraft",
    "wof:name": "Junkers G 23 Generalfieldmarchall von Hinderburg",
    "wof:placetype": "custom",
    "wof:placetype_alt": "aircraft",
    "wof:subordinate_of": [
      1159294171,
      1159292769
    ]
  },
  "geometry": {"coordinates":[12.2236,51.829379],"type":"Point"}
}
