{
  "type": "Feature",
  "properties": {
    "iso:country": "GB",
    "sfomuseum:aircraft_model": "Skua MK.II",
    "sfomuseum:aircraft_name": "Blackburn Skua MK.II",
    "sfomuseum:aircraft_variant": "Skua MK.II",
    "sfomuseum:count_objects_public": 0,
    "sfomuseum:is_sfo": 1,
    "sfomuseum:manufacturer": "Blackburn",
    "sfomuseum:placetype": "aircraft",
    "wof:name": "Blackburn Skua MK.II",
    "wof:placetype": "custom",
    "wof:placetype_alt": "aircraft",
    "wof:subordinate_of": [
      1159294057
    ]
  },
  "geometry": {"coordinates":[-1.247349,52.418788],"type":"Point"}
}
